rio_jobs/__init__.py
rio_jobs/components.py
rio_jobs-0.3.2.dist-info/METADATA
rio_jobs-0.3.2.dist-info/WHEEL
rio_jobs-0.3.2.dist-info/licenses/LICENSE.txt
rio_jobs-0.3.2.dist-info/RECORD
