Metadata-Version: 2.4
Name: rio-jobs
Version: 0.3.2
Summary: A job scheduler for the Rio pure Python web framework
Project-URL: homepage, https://github.com/rio-labs/rio-jobs
Project-URL: repository, https://github.com/rio-labs/rio-jobs
Author-email: Jakob Pinterits <jakob.pinterits@gmail.com>
License: Apache License
License-File: LICENSE.txt
Keywords: jobs,rio,scheduler,tasks,web framework
Classifier: Development Status :: 4 - Beta
Classifier: Intended Audience :: Developers
Classifier: License :: OSI Approved :: Apache Software License
Classifier: Programming Language :: Python :: 3
Classifier: Programming Language :: Python :: 3.10
Classifier: Programming Language :: Python :: 3.11
Classifier: Programming Language :: Python :: 3.12
Classifier: Programming Language :: Python :: 3.13
Requires-Python: >=3.10
Requires-Dist: rio-ui<0.12.0,>=0.11.0
